app_typer/__init__.py
app_typer/__main__.py
app_typer/main.py
app_typer-0.1.0.dist-info/entry_points.txt
app_typer-0.1.0.dist-info/WHEEL
app_typer-0.1.0.dist-info/METADATA
app_typer-0.1.0.dist-info/RECORD
