Metadata-Version: 2.1
Name: app-typer
Version: 0.1.0
Summary: 
Author: ysd
Author-email: helloysd@foxmail.com
Requires-Python: >=3.8,<4.0
Classifier: Programming Language :: Python :: 3
Classifier: Programming Language :: Python :: 3.8
Classifier: Programming Language :: Python :: 3.9
Requires-Dist: typer[all] (>=0.3.2,<0.4.0)
